android_category/__init__.py
android_category/android_category.py
android_category/cache.py
android_category/cli.py
android_category-0.0.4.dist-info/METADATA
android_category-0.0.4.dist-info/RECORD
android_category-0.0.4.dist-info/WHEEL
android_category-0.0.4.dist-info/entry_points.txt
android_category-0.0.4.dist-info/top_level.txt
