Metadata-Version: 2.1
Name: android-category
Version: 0.0.4
Summary: Tool to retrieve the category of an app given a url to the source code (git/local).
Home-page: https://github.com/luiscruz/android_category
Author: Luis Cruz
Author-email: luismirandacruz@gmail.com
License: UNKNOWN
Platform: UNKNOWN
Classifier: Programming Language :: Python :: 3
Classifier: License :: OSI Approved :: Apache Software License
Classifier: Operating System :: OS Independent
Requires-Dist: Click (==7.0)
Requires-Dist: GitPython (==2.1.11)
Requires-Dist: google-play-reader (>=0.0.1.dev16)
